setup.py
configdb/__init__.py
configdb/consolemsg.py
configdb/namespace.py
configdb.egg-info/PKG-INFO
configdb.egg-info/SOURCES.txt
configdb.egg-info/dependency_links.txt
configdb.egg-info/requires.txt
configdb.egg-info/top_level.txt