Metadata-Version: 1.1
Name: configdb
Version: 0.1
Summary: Quick way to store db connection details out of sources
Home-page: https://github.com/vokimon/python-configdb
Author: David Garcia Garzon
Author-email: voki@canvoki.net
License: GNU General Public License v3 or later (GPLv3+)
Platform: UNKNOWN
Classifier: Programming Language :: Python
Classifier: Programming Language :: Python :: 2
Classifier: Programming Language :: Python :: 3
Classifier: Topic :: Multimedia
Classifier: Topic :: Scientific/Engineering
Classifier: Topic :: Software Development :: Libraries :: Python Modules
Classifier: Intended Audience :: Developers
Classifier: Intended Audience :: Science/Research
Classifier: Development Status :: 5 - Production/Stable
Classifier: License :: OSI Approved :: GNU General Public License v3 or later (GPLv3+)
Classifier: Operating System :: OS Independent
